[
  {
    "operation": {
      "classname": "com.google.common.util.concurrent.Uninterruptibles",
      "name": "takeUninterruptibly",
      "parameterTypes": [
        "java.util.concurrent.BlockingQueue"
      ]
    },
    "identifiers": {
      "parameters": [
        "objCollectionQueue"
      ],
      "receiverName": "receiver",
      "returnName": "result"
    },
    "pre": [
      {
        "description": "objCollectionQueue must be non-empty",
        "guard": {
          "condition": "!objCollectionQueue.isEmpty()",
          "description": "objCollectionQueue must be non-empty"
        }
      }
    ],
    "post": [],
    "throws": []
  },
  {
    "operation": {
      "classname": "com.google.common.util.concurrent.AbstractFuture",
      "name": "get",
      "parameterTypes": []
    },
    "identifiers": {
      "parameters": [],
      "receiverName": "receiver",
      "returnName": "result"
    },
    "pre": [
      {
        "description": "receiver must be done or interrupted",
        "guard": {
          "condition": "receiver.isDone() || receiver.isCancelled()",
          "description": "receiver must be done or interrupted"
        }
      }
    ],
    "post": [],
    "throws": []
  },
  {
    "operation": {
      "classname": "com.google.common.math.BigIntegerMath",
      "name": "factorial",
      "parameterTypes": [
        "int"
      ]
    },
    "identifiers": {
      "parameters": [
        "n"
      ],
      "receiverName": "receiver",
      "returnName": "result"
    },
    "pre": [
      {
        "description": "n must be non-negative and small enough to prevent excessive computation",
        "guard": {
          "condition": "n >= 0 && n <= 170",
          "description": "n is between 0 and 170 (inclusive)"
        }
      }
    ],
    "post": [],
    "throws": []
  }
]
